{
  "tool.hint.elastic.remove": "Poista",
  "tool.hint.rope.remove": "Poista",
  "tool.hint.wheeltool.place": "Aseta",
  "tool.hint.weld.stage0": "Yhdistää kaksi esinettä",
  "tool.hint.ballsocket.remove": "Poista",
  "tool.hint.duplicator.copy": "Kopioi",
  "tool.hint.balloon.place_rope": "Aseta (köysi)",
  "tool.hint.wheeltool.description": "Liittää pyörän objektiin",
  "tool.hint.weld.remove": "Irrota",
  "tool.hint.duplicator.description": "Käytetään koko laitteiden kopioimiseen, liittämiseen ja tallentamiseen",
  "tool.hint.slider.secondary.stage1": "Peruuta",
  "tool.hint.slider.remove": "Poista",
  "tool.hint.weld.confirm": "Vahvista",
  "tool.hint.remover.remove": "Poista",
  "tool.hint.thrustertool.toggle_axis": "Vaihda akseli",
  "tool.hint.balloon.place": "Aseta",
  "tool.hint.weld.stage1": "Valitse toinen esine hitsattavaksi",
  "tool.hint.weld.stage2": "Käännä objekti",
  "tool.hint.thrustertool.description": "Liittää työntimen objektiin",
  "tool.hint.balloon.description": "Asettaa puhkeavan ilmapallon",
  "tool.hint.decaltool.place": "Aseta",
  "tool.hint.duplicator.place": "Aseta",
  "tool.hint.elastic.source": "Valitse lähde",
  "tool.hint.nocollide.source": "Valitse lähde",
  "tool.hint.rope.stage0": "Yhdistää kaksi esinettä köydellä",
  "tool.hint.rope.stage1": "Valitse toinen objekti",
  "tool.hint.elastic.stage1": "Valitse toinen objekti",
  "tool.hint.nocollide.remove": "Poista",
  "tool.hint.elastic.stage0": "Yhdistää kaksi objektia joustavalla",
  "tool.hint.ballsocket.stage0": "Yhdistää kaksi objektia pallokytkimellä",
  "tool.hint.rope.finish": "Valmis",
  "tool.hint.ballsocket.source": "Valitse lähde",
  "tool.hint.wheeltool.toggle_direction": "Vaihda suunta",
  "tool.hint.rope.source": "Valitse lähde",
  "tool.hint.hydraulictool.stage1": "Valitse toinen objekti",
  "tool.hint.hydraulictool.source": "Valitse lähde",
  "tool.hint.hydraulictool.finish": "Valmis",
  "tool.hint.hydraulictool.remove": "Poista",
  "tool.hint.weld.source": "Valitse lähde",
  "tool.hint.elastic.finish": "Valmis",
  "tool.hint.linker.source": "Valitse lähde",
  "tool.hint.linker.finish": "Valmis",
  "tool.hint.weld.finish": "Valmis",
  "tool.hint.wheeltool.toggle_axis": "Vaihda akseli",
  "tool.hint.hoverballtool.place": "Aseta",
  "tool.hint.thrustertool.place": "Aseta",
  "tool.hint.emittertool.place": "Aseta",
  "tool.hint.ballsocket.stage1": "Valitse toinen objekti",
  "tool.hint.thrustertool.place_no_weld": "Aseta (ilman hitsausta)",
  "tool.hint.slider.finish": "Valmis",
  "tool.hint.ballsocket.finish": "Valmis",
  "tool.hint.slider.stage1": "Valitse toinen objekti",
  "tool.hint.keepupright.cancel": "Peruuta",
  "tool.hint.keepupright.remove": "Poista",
  "tool.hint.remover.description": "Poistaa esineitä maailmasta",
  "tool.hint.slider.secondary": "Normaalisti",
  "tool.hint.resizer.description": "Muokkaa objektin kokoa",
  "tool.hint.nocollide.stage0": "Poistaa törmäyksen kahden objektin välillä",
  "tool.hint.nocollide.stage1": "Valitse toinen objekti",
  "tool.hint.slider.stage0": "Yhdistää kaksi objektia liukuvalla nivelillä",
  "tool.hint.mass.description": "Asettaa objektin massan",
  "tool.hint.resizer.grow": "Kasva",
  "tool.hint.unbreakable.description": "Tekee objektista vahingoittumattoman",
  "tool.hint.slider.source": "Valitse lähde",
  "tool.hint.decaltool.paint": "Maali",
  "tool.hint.decaltool.description": "Suihkuttaa tarroja pinnoille",
  "tool.hint.nocollide.finish": "Valmis",
  "tool.hint.hydraulictool.stage0": "Yhdistää kaksi objektia hydraulisella mäntällä",
  "tool.hint.mass.set": "Aseta massa",
  "tool.hint.mass.reset": "Nollaa massa",
  "tool.hint.resizer.reset": "Nollaa",
  "tool.hint.unbreakable.set": "Aseta Murtumattomaksi",
  "tool.hint.mass.copy": "Kopioi massa",
  "tool.hint.linker.stage0": "Luodaan linkki kahden objektin välille, jotta ne käsitellään yhtenä laitteena.",
  "tool.hint.resizer.shrink": "Pienennä",
  "tool.hint.hoverballtool.description": "Liittää hoverballin, joka pitää esineet tietyssä korkeudessa",
  "tool.hint.linker.remove": "Poista linkitys",
  "tool.hint.linker.stage1": "Valitse toinen objekti linkitettäväksi",
  "tool.hint.unbreakable.unset": "Nollaa",
  "tool.hint.emittertool.description": "Asettaa konfiguroitavan hiukkaspäästön",
  "tool.hint.keepupright.description": "Rajoittaa objektin pysymään pystyssä",
  "tool.group.tools": "Työkalut",
  "tool.hint.keepupright.stage1": "Valitse toinen objekti linkitettäväksi",
  "tool.hint.keepupright.apply_world": "Käytä (ankkuroi maailmaan)",
  "tool.hint.keepupright.start_link": "Valitse ensimmäinen objekti",
  "tool.hint.keepupright.finish": "Viimeistele linkki",
  "tool.hint.stacker.cycle_alignment": "Syklin kohdistus",
  "tool.hint.stacker.description": "Kopioi objekteja suuntaan reaaliaikaisella esikatselulla",
  "tool.hint.stacker.cycle_direction": "Kierrä Suunta",
  "tool.hint.stacker.stack": "Pino",
  "tool.name.elastic": "Joustava",
  "tool.name.weld": "Weld",
  "tool.name.hydraulic": "Hydraulinen",
  "tool.name.rope": "Köysi",
  "tool.name.mass": "Massa",
  "tool.name.stacker": "Stacker",
  "tool.name.unbreakable": "Murtumaton",
  "tool.name.thruster": "Thruster",
  "tool.name.remover": "Poistaja",
  "tool.name.linker": "Linkkeri",
  "tool.name.trail": "Polku",
  "tool.name.nocollide": "Ei törmäystä",
  "tool.name.resizer": "Koonmuuttaja",
  "tool.name.balloon": "Ilmapallo",
  "tool.name.decal": "Decal",
  "tool.name.ballsocket": "Pallon liitos",
  "tool.name.slider": "Liukusäädin",
  "tool.group.constraints": "Rajoitukset",
  "tool.name.keepupright": "Pysty",
  "tool.group.building": "Rakentaminen",
  "tool.name.duplicator": "Kopioija",
  "tool.name.wheel": "Rengas",
  "tool.group.render": "Render",
  "tool.name.emitter": "Emitter",
  "tool.name.hoverball": "Hoverball"
}